[
    {
        "img": "http://img3.yun300.cn/repository/image/-BxJV09BTLemK-7z4a9cmQ.jpg?tenantId=102567&viewType=1&k=1621911502000_640xaf.jpg?tenantId=102567&viewType=1&k=1621911502000http://img3.yun300.cn/repository/image/-BxJV09BTLemK-7z4a9cmQ.jpg?tenantId=102567&viewType=1&k=1621911502000_640xaf.jpg?tenantId=102567&viewType=1&k=1621911502000http://img3.yun300.cn/repository/image/-BxJV09BTLemK-7z4a9cmQ.jpg?tenantId=102567&viewType=1&k=1621911502000_640xaf.jpg?tenantId=102567&viewType=1&k=1621911502000http://img3.yun300.cn/repository/image/-BxJV09BTLemK-7z4a9cmQ.jpg?tenantId=102567&viewType=1&k=1621911502000_640xaf.jpg?tenantId=102567&viewType=1&k=1621911502000http://img3.yun300.cn/repository/image/-BxJV09BTLemK-7z4a9cmQ.jpg?tenantId=102567&viewType=1&k=1621911502000_640xaf.jpg?tenantId=102567&viewType=1&k=1621911502000http://img3.yun300.cn/repository/image/-BxJV09BTLemK-7z4a9cmQ.jpg?tenantId=102567&viewType=1&k=1621911502000_640xaf.jpg?tenantId=102567&viewType=1&k=1621911502000http://img3.yun300.cn/repository/image/-BxJV09BTLemK-7z4a9cmQ.jpg?tenantId=102567&viewType=1&k=1621911502000_640xaf.jpg?tenantId=102567&viewType=1&k=1621911502000http://img3.yun300.cn/repository/image/-BxJV09BTLemK-7z4a9cmQ.jpg?tenantId=102567&viewType=1&k=1621911502000_640xaf.jpg?tenantId=102567&viewType=1&k=1621911502000",
        "title": "面膜正确的使用方法",
        "time": "2020-09-15 ",
        "text": "面膜是我们经常使用的护肤品。补水面膜的普及更是让每家每户都有备用着几片面膜，不过因为面膜的简单实用的使用而让很多人都不注意面膜的使用方法。"
    },
    {
        "img": "http://img3.yun300.cn/repository/image/51-sBgyqSle8xpXEHNrzjQ.jpg?tenantId=102567&viewType=1&k=1621911502000_640xaf.jpg?tenantId=102567&viewType=1&k=1621911502000",
        "title": "夏季头皮养护，要清凉才够爽",
        "time": "2019-06-12 ",
        "text": "夏季天气炎热，比较容易出汗，当然头发也是湿湿的，所以很多人洗头会比较勤。那要怎样正确洗头呢？如果没有正确的养护头皮，长期以来会让头发变得很干枯，严重的时候会对秀发造成严重的影响。下面就给大家介绍一下夏季洗头的小妙招。1：洗发之前要先梳发。这是很多人都容易忽视的细节。梳理不仅可促进头部皮肤的血液循环，减少头发的缠绕磨损及洗发时造成断发，同时还可以清理头皮上的脏东西和鳞屑，方便下一步的清洗。所以，洗头"
    },
    {
        "img": "http://img3.yun300.cn/repository/image/585-3VUhQtup2PswqhIIMg.jpg?tenantId=102567&viewType=1&k=1621911502000_640xaf.jpg?tenantId=102567&viewType=1&k=1621911502000",
        "title": "蜂蜜与护发",
        "time": "2019-04-22 ",
        "text": "《养生论》：“春三月，宜养发”，蜂蜜作为“天然营养剂”，富含多种氨基酸和营养物质，可以滋养润泽秀发。蜂蜜护发的八大功效......"
    },
    {
        "img": "http://img3.yun300.cn/repository/image/sAaD8oRsRl2AA1VE1HK1KQ.jpg?tenantId=102567&viewType=1&k=1621911502000_640xaf.jpg?tenantId=102567&viewType=1&k=1621911502000",
        "title": "香水洗护发小常识",
        "time": "2019-01-08 ",
        "text": "蜂花香氛系列洗护发产品由香水配方师精心配制，采用植物精萃物、天然香料调制出的，与香水一样，分为前调、中调和尾调，前调......"
    },
    {
        "img": "http://img3.yun300.cn/repository/image/YpZr_jTnSEeC33TGgxEU1g.jpg?tenantId=102567&viewType=1&k=1621911502000_640xaf.jpg?tenantId=102567&viewType=1&k=1621911502000",
        "title": "格拉斯与芳香文化",
        "time": "2018-12-21 ",
        "text": "香水这个词，从拉丁文“perfumum”衍生而来，意思是“穿透烟雾”。旧约圣经提到香水，通常指一种香料形成，这与拉丁文定义相符......"
    },
    {
        "img": "http://img3.yun300.cn/repository/image/m10JE0VFSPyIU2nK3ifEJg.jpg?tenantId=102567&viewType=1&k=1621911502000_640xaf.jpg?tenantId=102567&viewType=1&k=1621911502000",
        "title": "精油护发小贴士",
        "time": "2018-12-19 ",
        "text": "精油作用于头皮，通过对皮脂调节，抑制脱发，促进毛发生长，所以一大部分精油是在洗发之前使用的，均匀涂抹发根，即可改善发质的作用"
    },
    {
        "img": "http://img3.yun300.cn/repository/image/oZimVYO2QtCRYtTP-F8vVw.png?tenantId=102567&viewType=1&k=1621911502000_640xaf.png?tenantId=102567&viewType=1&k=1621911502000",
        "title": "春季护发小常识",
        "time": "2018-12-11 ",
        "text": "《黄帝内经》里说：“春主生发，夏主生长。”春季，是万物复苏的季节。气温慢慢的回升，体内血液循环速度明显加快，营养物质更多、更容易进入到表皮微循环系统......"
    },
    {
        "img": "http://img3.yun300.cn/repository/image/E5Es4UR0SDi75SL5C9cctw.png?tenantId=102567&viewType=1&k=1621911502000_640xaf.png?tenantId=102567&viewType=1&k=1621911502000",
        "title": "秋季护发小常识",
        "time": "2018-11-12 ",
        "text": "秋冬季节不仅多风而且气候干燥，平时保养顺滑的秀发在秋冬季很容易缺少水分而出现问题，因此秋冬季护发让许多人异常重视......"
    },
    {
        "img": "",
        "title": "",
        "time": "",
        "text": ""
    }
]